pytorch_utils/__init__.py
pytorch_utils/nb_figure.py
pytorch_utils/sacred_trainer.py
pytorch_utils/train_utils.py
pytorch_utils/updaters.py
pytorch_utils/wrapped_lstm.py
pytorch_utils/wrapped_rnn.py
pytorch_utils-0.4.dist-info/DESCRIPTION.rst
pytorch_utils-0.4.dist-info/METADATA
pytorch_utils-0.4.dist-info/RECORD
pytorch_utils-0.4.dist-info/WHEEL
pytorch_utils-0.4.dist-info/metadata.json
pytorch_utils-0.4.dist-info/top_level.txt
